confapp/__init__.py
confapp/load_config.py
confapp/settings_manager.py
confapp_shaliulab-1.1.13.dist-info/LICENSE
confapp_shaliulab-1.1.13.dist-info/METADATA
confapp_shaliulab-1.1.13.dist-info/WHEEL
confapp_shaliulab-1.1.13.dist-info/top_level.txt
confapp_shaliulab-1.1.13.dist-info/RECORD
