Metadata-Version: 2.1
Name: confapp-shaliulab
Version: 1.1.13
Summary: Python library that implements a singleton object to use as settings system.
Home-page: https://github.com/UmSenhorQualquer/confapp
Author: Ricardo Jorge Vieira Ribeiro
Author-email: ricardojvr@gmail.com
Classifier: Intended Audience :: Developers
Classifier: Operating System :: OS Independent
Classifier: Programming Language :: Python
Classifier: Programming Language :: Python :: 2.7
Classifier: Programming Language :: Python :: 3
License-File: LICENSE
